{
  "_doc": "Byte-to-Unicode map for the OLCKOptimum-Medium and OLCKOptimum-ExtraBlack legacy display fonts. Their cmaps address Ol Chiki glyph outlines with printable ASCII source codes, so extracted PDF text requires a legacy-byte conversion. The public source is the Internet Archive item aale-chhatka-pdf-e-magazine-2023, PDF SHA-256 7588dae38adb5533e5692bf6cf6148cb5e411afa32c4f24dfe7cd1db1b9ec9b8; further evidence is documented in docs/EVIDENCE.md.",
  "_derivation": "Derived from normalized rendered-outline comparison against Unicode Ol Chiki references, constrained by corpus position and the structure of the Ol Chiki alphabet. The Optimum Medium and ExtraBlack fonts share this effective layout. OLCKLatic is a separately evidenced layout applied through the fixed overlay in olchiki.py; it is not encoded in this Optimum base resource.",
  "_confidence": "The confirmed inventory contains 52 letter or modifier sources, ten digit sources, and one punctuation source; no uncertain Optimum source remains. Lowercase n maps to U+1C71 OL CHIKI LETTER EN and uppercase T maps to U+1C5B OL CHIKI LETTER AT. Twenty uppercase and lowercase source pairs have identical outlines and intentionally share targets; d/D, h/H, m/M, n/N, o/O, and t/T are distinct. Uppercase W and X are included from exact outline identity with lowercase w and x rather than corpus occurrence.",
  "_uncertain_bytes": [],
  "map": {
    "30": ["1C50"],
    "31": ["1C51"],
    "32": ["1C52"],
    "33": ["1C53"],
    "34": ["1C54"],
    "35": ["1C55"],
    "36": ["1C56"],
    "37": ["1C57"],
    "38": ["1C58"],
    "39": ["1C59"],

    "61": ["1C5F"],
    "62": ["1C75"],
    "63": ["1C6A"],
    "64": ["1C70"],
    "65": ["1C6E"],
    "66": ["1C5D"],
    "67": ["1C5C"],
    "68": ["1C66"],
    "69": ["1C64"],
    "6A": ["1C61"],
    "6B": ["1C60"],
    "6C": ["1C5E"],
    "6D": ["1C62"],
    "6E": ["1C71"],
    "6F": ["1C5A"],
    "70": ["1C6F"],
    "71": ["1C67"],
    "72": ["1C68"],
    "73": ["1C65"],
    "74": ["1C74"],
    "75": ["1C69"],
    "76": ["1C63"],
    "77": ["1C76"],
    "78": ["1C7D"],
    "79": ["1C6D"],
    "7A": ["1C72"],

    "44": ["1C6B"],
    "48": ["1C77"],
    "4D": ["1C6C"],
    "4E": ["1C78"],
    "4F": ["1C73"],

    "41": ["1C5F"],
    "42": ["1C75"],
    "43": ["1C6A"],
    "45": ["1C6E"],
    "46": ["1C5D"],
    "47": ["1C5C"],
    "49": ["1C64"],
    "4A": ["1C61"],
    "4B": ["1C60"],
    "4C": ["1C5E"],
    "50": ["1C6F"],
    "51": ["1C67"],
    "52": ["1C68"],
    "53": ["1C65"],
    "54": ["1C5B"],
    "55": ["1C69"],
    "56": ["1C63"],
    "57": ["1C76"],
    "58": ["1C7D"],
    "59": ["1C6D"],
    "5A": ["1C72"],

    "7C": ["1C7E"]
  },
  "uncertain_map": {}
}
